aioevent/__init__.py
aioevent/decorator.py
aioevent/emitter.py
aioevent/event.py
aioevent/subscription.py
aioevent-1.4.0.dist-info/METADATA
aioevent-1.4.0.dist-info/RECORD
aioevent-1.4.0.dist-info/WHEEL
aioevent-1.4.0.dist-info/top_level.txt
test/__init__.py
test/test_context_manager.py
test/test_decorator.py
test/test_emitter.py
test/test_event_multiple_inheritance.py
test/test_proxy.py
