Metadata-Version: 2.1
Name: aioevent
Version: 1.4.0
Summary: Events for asyncio.
Home-page: UNKNOWN
Author: Travis DePrato
Author-email: travisdeprato@gmail.com
License: UNKNOWN
Platform: UNKNOWN
Requires-Python: >=3.6
